{
  "cuda": {
    "value": true
  },
  "seed": {
    "value": 42
  },
  "model": {
    "value": "resnet50"
  },
  "_wandb": {
    "value": {
      "m": [],
      "t": {
        "1": [1, 5, 41, 49, 51, 53, 55],
        "2": [1, 5, 41, 49, 51, 53, 55],
        "3": [2, 15, 16, 23, 55, 62],
        "4": "3.10.16",
        "5": "0.19.6",
        "8": [5],
        "10": [19],
        "12": "0.19.6",
        "13": "linux-x86_64"
      },
      "visualize": {
        "confusion_matrix_best_val_epoch": {
          "panel_type": "Vega2",
          "panel_config": {
            "transform": {
              "name": "tableWithLeafColNames"
            },
            "userQuery": {
              "queryFields": [
                {
                  "args": [
                    {
                      "name": "runSets",
                      "value": "${runSets}"
                    }
                  ],
                  "name": "runSets",
                  "fields": [
                    {
                      "name": "id",
                      "fields": []
                    },
                    {
                      "name": "name",
                      "fields": []
                    },
                    {
                      "name": "_defaultColorIndex",
                      "fields": []
                    },
                    {
                      "args": [
                        {
                          "name": "tableKey",
                          "value": "confusion_matrix_best_val_epoch_table"
                        }
                      ],
                      "name": "summaryTable",
                      "fields": []
                    }
                  ]
                }
              ]
            },
            "panelDefId": "wandb/confusion_matrix/v1",
            "fieldSettings": {
              "Actual": "Actual",
              "Predicted": "Predicted",
              "nPredictions": "nPredictions"
            },
            "stringSettings": {
              "title": "Confusion Matrix Curve"
            }
          }
        }
      },
      "cli_version": "0.19.6",
      "python_version": "3.10.16"
    }
  },
  "epochs": {
    "value": 50
  },
  "patience": {
    "value": 10
  },
  "dropout_p": {
    "value": 0.4
  },
  "optimizer": {
    "value": "AdamW"
  },
  "scheduler": {
    "value": "plateau"
  },
  "batch_size": {
    "value": 32
  },
  "input_size": {
    "value": 224
  },
  "dataset_std": {
    "value": null
  },
  "mixup_alpha": {
    "value": 0.2
  },
  "num_classes": {
    "value": 13
  },
  "cutmix_alpha": {
    "value": 1
  },
  "dataset_mean": {
    "value": null
  },
  "dataset_name": {
    "value": "dushj98/aerial_real_plus_0100"
  },
  "weight_decay": {
    "value": 0.04
  },
  "augment_level": {
    "value": "none"
  },
  "learning_rate": {
    "value": 0.000007
  },
  "training_mode": {
    "value": "fft"
  },
  "cutmix_or_mixup": {
    "value": true
  },
  "label_smoothing": {
    "value": 0
  },
  "calc_dataset_stats": {
    "value": false
  },
  "layers_to_unfreeze": {
    "value": []
  },
  "use_mixed_precision": {
    "value": true
  },
  "actual_use_mixed_precision": {
    "value": true
  },
  "data_normalization_strategy": {
    "value": "ImageNet"
  },
  "_runtime": 2574.160023681,
  "_step": 38,
  "_timestamp": 1748533952.4728196,
  "_wandb.runtime": 2574,
  "acc/train": 0,
  "acc/val": 0.4880239520958084,
  "best_epoch": 27,
  "best_val_acc": 0.49792722247812066,
  "best_val_f1": 0.4864492748526112,
  "best_val_loss": 1.557434039970303,
  "confusion_matrix_best_val_epoch_table": {
    "_latest_artifact_path": "wandb-client-artifact://y7jfrkyanbx4exl7c0nb9zokvfv4bjljwjarjcabe6wfgu11dhgqywa53rhffba96rddcxd6k94phkc3os7mjwp2tw7sxb166w049etudszpy8wvjkbt6271dsfhxz8y:latest/confusion_matrix_best_val_epoch_table.table.json",
    "_type": "table-file",
    "artifact_path": "wandb-client-artifact://5sn8vglc0tseyobt3bg788q6y43ju7zusoo866y1uplluqr33139o9oj9kgxl19e7vfexf8879beopfjd47n8qmcd30yl46krlkas6pn5y2gu3wdlbzmodlw9xn9ry0h/confusion_matrix_best_val_epoch_table.table.json",
    "ncols": 3,
    "nrows": 169,
    "path": "media/table/confusion_matrix_best_val_epoch_table_38_12331c5f2853a53e4385.table.json",
    "sha256": "12331c5f2853a53e438565b71781270388cda9f23dd1fd7bd4c80ea80e53f781",
    "size": 8882
  },
  "epoch": 37,
  "epochs_since_improvement": 10,
  "f1/train": 0,
  "f1/val": 0.4733371259631939,
  "final_learning_rate": 2.8e-7,
  "loss/train": 0.9511242421319396,
  "loss/val": 1.596450418933972,
  "precision/train": 0,
  "precision/val": 0.4766107868559448,
  "recall/train": 0,
  "recall/val": 0.4880239520958084
}
