{
    "cuda": {
      "value": true
    },
    "seed": {
      "value": 42
    },
    "model": {
      "value": "resnet50"
    },
    "_wandb": {
      "value": {
        "m": [],
        "t": {
          "1": [
            1,
            5,
            41,
            49,
            51,
            53,
            55
          ],
          "2": [
            1,
            5,
            41,
            49,
            51,
            53,
            55
          ],
          "3": [
            2,
            15,
            16,
            23,
            55,
            62
          ],
          "4": "3.10.16",
          "5": "0.19.6",
          "8": [
            5
          ],
          "10": [
            19
          ],
          "12": "0.19.6",
          "13": "linux-x86_64"
        },
        "visualize": {
          "confusion_matrix_best_val_epoch": {
            "panel_type": "Vega2",
            "panel_config": {
              "transform": {
                "name": "tableWithLeafColNames"
              },
              "userQuery": {
                "queryFields": [
                  {
                    "args": [
                      {
                        "name": "runSets",
                        "value": "${runSets}"
                      }
                    ],
                    "name": "runSets",
                    "fields": [
                      {
                        "name": "id",
                        "fields": []
                      },
                      {
                        "name": "name",
                        "fields": []
                      },
                      {
                        "name": "_defaultColorIndex",
                        "fields": []
                      },
                      {
                        "args": [
                          {
                            "name": "tableKey",
                            "value": "confusion_matrix_best_val_epoch_table"
                          }
                        ],
                        "name": "summaryTable",
                        "fields": []
                      }
                    ]
                  }
                ]
              },
              "panelDefId": "wandb/confusion_matrix/v1",
              "fieldSettings": {
                "Actual": "Actual",
                "Predicted": "Predicted",
                "nPredictions": "nPredictions"
              },
              "stringSettings": {
                "title": "Confusion Matrix Curve"
              }
            }
          }
        },
        "cli_version": "0.19.6",
        "python_version": "3.10.16"
      }
    },
    "epochs": {
      "value": 50
    },
    "patience": {
      "value": 10
    },
    "dropout_p": {
      "value": 0.2
    },
    "optimizer": {
      "value": "AdamW"
    },
    "scheduler": {
      "value": "plateau"
    },
    "batch_size": {
      "value": 32
    },
    "input_size": {
      "value": 224
    },
    "dataset_std": {
      "value": null
    },
    "mixup_alpha": {
      "value": 0.2
    },
    "num_classes": {
      "value": 13
    },
    "cutmix_alpha": {
      "value": 1
    },
    "dataset_mean": {
      "value": null
    },
    "dataset_name": {
      "value": "dushj98/aerial_real_plus_0050"
    },
    "weight_decay": {
      "value": 0.19
    },
    "augment_level": {
      "value": "none"
    },
    "learning_rate": {
      "value": 0.000007
    },
    "training_mode": {
      "value": "sft"
    },
    "cutmix_or_mixup": {
      "value": true
    },
    "label_smoothing": {
      "value": 0
    },
    "calc_dataset_stats": {
      "value": false
    },
    "layers_to_unfreeze": {
      "value": [
        "layer4."
      ]
    },
    "use_mixed_precision": {
      "value": true
    },
    "actual_use_mixed_precision": {
      "value": true
    },
    "data_normalization_strategy": {
      "value": "ImageNet"
    },
    "_runtime": 2324.699817541,
    "_step": 43,
    "_timestamp": 1748516133.0682871,
    "_wandb.runtime": 2324,
    "acc/train": 0,
    "acc/val": 0.4748963611239061,
    "best_epoch": 32,
    "best_val_acc": 0.4841087056655919,
    "best_val_f1": 0.4695021851034519,
    "best_val_loss": 1.5927268873980824,
    "confusion_matrix_best_val_epoch_table": {
      "_latest_artifact_path": "wandb-client-artifact://6qi88pmc7vdc4yea64198xuxb6xto0knhuds9vcrp2fgz5u1sy3ofi4hgse37341phjz4pns5jhgs4k0ptsi013qc60wsv68ksjt3hjhiteryg8mpblu8mp3hhel9wv3:latest/confusion_matrix_best_val_epoch_table.table.json",
      "_type": "table-file",
      "artifact_path": "wandb-client-artifact://9wm0jb3kwjr5ujd5mkw8wl8ef8a1r5qeglgbudfuheoulx65629vh5s3jcf1oyzma1dlkfkdm8icw2o2zgqfef445aijvjwj86os35ky2vf9h3ctuqmgufdou01ar175/confusion_matrix_best_val_epoch_table.table.json",
      "ncols": 3,
      "nrows": 169,
      "path": "media/table/confusion_matrix_best_val_epoch_table_43_e6edc524bbc27be5fc9a.table.json",
      "sha256": "e6edc524bbc27be5fc9ae59ad7bf0668b75125d7e3d3e5db3d7207af4d7c66c5",
      "size": 8885
    },
    "epoch": 42,
    "epochs_since_improvement": 10,
    "f1/train": 0,
    "f1/val": 0.464761781187051,
    "final_learning_rate": 0.0000014,
    "loss/train": 1.1852312972260703,
    "loss/val": 1.6068476771825142,
    "precision/train": 0,
    "precision/val": 0.4675598954172393,
    "recall/train": 0,
    "recall/val": 0.4748963611239061
  }